Metadata-Version: 2.1
Name: Blauwal3-Textable
Version: 3.1.11
Summary: 蓝鲸数据挖掘软件包的文本分析附加组件。
Home-page: http://textable.io
Download-URL: https://github.com/axanthos/orange3-textable/archive/master.zip
Author: LangTech Sarl
Author-email: info@langtech.ch
License: GPLv3
Keywords: text mining,text analysis,textable,orange3,orange3 add-on
Classifier: Development Status :: 5 - Production/Stable
Classifier: Environment :: X11 Applications :: Qt
Classifier: Environment :: Plugins
Classifier: Programming Language :: Python :: 3 :: Only
Classifier: License :: OSI Approved :: GNU General Public License v3 or later (GPLv3+)
Classifier: Operating System :: OS Independent
Classifier: Topic :: Scientific/Engineering :: Information Analysis
Classifier: Topic :: Text Processing :: General
Classifier: Topic :: Text Processing :: Linguistic
Classifier: Topic :: Software Development :: Libraries :: Python Modules
Classifier: Intended Audience :: Education
Classifier: Intended Audience :: Science/Research
License-File: LICENSE
Requires-Dist: Blauwal3>=3.14.0
Requires-Dist: setuptools
Requires-Dist: future
Requires-Dist: LTTL>=2.0.12
Requires-Dist: chardet
Requires-Dist: treetaggerwrapper
Requires-Dist: appdirs
Requires-Dist: pycountry
